{
  "version": 1,
  "snapshot_calendar": "America/New_York",
  "by_date": {
    "2026-04-02": {
      "snapshot_date": "2026-04-02",
      "ts_utc": "2026-04-02T22:03:50.298287+00:00",
      "score": 100,
      "score_uncapped": 340,
      "overall_risk": "heavy_stress",
      "critical_count": 6,
      "warning_count": 12,
      "leading_signal_count": 11,
      "source": "github_actions",
      "github_sha": "d7a2052c791432f16ce38616a038bc73e206a834",
      "github_run_id": "23924042189"
    },
    "2026-04-03": {
      "snapshot_date": "2026-04-03",
      "ts_utc": "2026-04-03T21:59:00.322144+00:00",
      "score": 100,
      "score_uncapped": 338,
      "overall_risk": "heavy_stress",
      "critical_count": 6,
      "warning_count": 12,
      "leading_signal_count": 10,
      "source": "github_actions",
      "github_sha": "53ab9bd89ab684d616fd94fdbdd4e378cce7adb6",
      "github_run_id": "23963711013"
    },
    "2026-04-06": {
      "snapshot_date": "2026-04-06",
      "ts_utc": "2026-04-06T22:01:23.807487+00:00",
      "score": 100,
      "score_uncapped": 339,
      "overall_risk": "heavy_stress",
      "critical_count": 5,
      "warning_count": 12,
      "leading_signal_count": 9,
      "source": "github_actions",
      "github_sha": "bf33a6a9aa7fe83bbdae6ec9b4987e219c737e91",
      "github_run_id": "24053335672"
    },
    "2026-03-30": {
      "snapshot_date": "2026-03-30",
      "ts_utc": "2026-03-30T22:29:41.426226+00:00",
      "score": 100,
      "score_uncapped": 744,
      "overall_risk": "catastrophic",
      "critical_count": 14,
      "warning_count": 27,
      "leading_signal_count": 11,
      "source": "github_actions"
    },
    "2026-03-31": {
      "snapshot_date": "2026-03-31",
      "ts_utc": "2026-03-31T22:05:14.011471+00:00",
      "score": 100,
      "score_uncapped": 287,
      "overall_risk": "catastrophic",
      "critical_count": 4,
      "warning_count": 12,
      "leading_signal_count": 11,
      "source": "github_actions"
    },
    "2026-04-01": {
      "snapshot_date": "2026-04-01",
      "ts_utc": "2026-04-01T22:05:10.752177+00:00",
      "score": 100,
      "score_uncapped": 447,
      "overall_risk": "catastrophic",
      "critical_count": 9,
      "warning_count": 15,
      "leading_signal_count": 11,
      "source": "github_actions"
    },
    "2026-04-07": {
      "snapshot_date": "2026-04-07",
      "ts_utc": "2026-04-07T18:14:46.529100+00:00",
      "score": 100,
      "score_uncapped": 484,
      "overall_risk": "heavy_stress",
      "critical_count": 8,
      "warning_count": 18,
      "leading_signal_count": 10,
      "source": "github_actions",
      "github_sha": "8fdd7b87290cbb189d50265a0e638ed05565ebac",
      "github_run_id": "24097045387"
    }
  }
}
